amqp_bundle/__init__.py
amqp_bundle/bundle.py
amqp_bundle-1.1.dist-info/DESCRIPTION.rst
amqp_bundle-1.1.dist-info/METADATA
amqp_bundle-1.1.dist-info/RECORD
amqp_bundle-1.1.dist-info/WHEEL
amqp_bundle-1.1.dist-info/metadata.json
amqp_bundle-1.1.dist-info/top_level.txt
