Metadata-Version: 2.0
Name: amqp-bundle
Version: 1.1
Summary: Remote events through amqp
Home-page: https://github.com/applauncher-team/amqp_bundle
Author: Alvaro Garcia Gomez
Author-email: maxpowel@gmail.com
License: UNKNOWN
Download-URL: https://github.com/applauncher-team/amqp__bundle/archive/master.zip
Keywords: applauncher,amqp
Platform: UNKNOWN
Classifier: Topic :: Adaptive Technologies
Classifier: Topic :: Software Development
Classifier: Topic :: System
Classifier: Topic :: Utilities
Requires-Dist: applauncher (==1.44)
Requires-Dist: kombu (==4.6.5)
